caffeinism_utils/__init__.py
caffeinism_utils/aiteration.py
caffeinism_utils/asyncio.py
caffeinism_utils/av/__init__.py
caffeinism_utils/av/codecs.py
caffeinism_utils/av/filters.py
caffeinism_utils/av/io.py
caffeinism_utils/av/utils.py
caffeinism_utils/http.py
caffeinism_utils/io.py
caffeinism_utils/iteration.py
caffeinism_utils/prefetch.py
caffeinism_utils/utils.py
caffeinism_utils/zip.py
caffeinism_utils-0.0.183.dist-info/METADATA
caffeinism_utils-0.0.183.dist-info/WHEEL
caffeinism_utils-0.0.183.dist-info/RECORD
