Metadata-Version: 2.4
Name: caffeinism-utils
Version: 0.0.183
Summary: 
Author: Kim Minjong
Author-email: make.dirty.code@gmail.com
Requires-Python: >=3.8,<4.0
Classifier: Programming Language :: Python :: 3
Classifier: Programming Language :: Python :: 3.8
Classifier: Programming Language :: Python :: 3.9
Classifier: Programming Language :: Python :: 3.10
Classifier: Programming Language :: Python :: 3.11
Classifier: Programming Language :: Python :: 3.12
Classifier: Programming Language :: Python :: 3.13
Classifier: Programming Language :: Python :: 3.14
Provides-Extra: av
Requires-Dist: asyncstdlib (>=3.13.1,<4.0.0)
Requires-Dist: audioop-lts (>=0.2.1,<0.3.0) ; extra == "av"
Requires-Dist: av (>=16.0.0,<17.0.0) ; extra == "av"
Requires-Dist: numba (>=0.62.1,<0.63.0) ; extra == "av"
Requires-Dist: numpy (<2) ; extra == "av"
Requires-Dist: pydub (>=0.25.1,<0.26.0) ; extra == "av"
